{
  "collected_at": "2026-07-18T19:30:29.585680+00:00",
  "language": "",
  "since": "daily",
  "repos": [
    {
      "rank": 1,
      "owner": "Robbyant",
      "name": "lingbot-map",
      "url": "https://github.com/Robbyant/lingbot-map",
      "description": "A feed-forward 3D foundation model for reconstructing scenes from streaming data",
      "language": "Python",
      "stars": "12,747",
      "forks": "1,332",
      "stars_today": "827 stars today"
    },
    {
      "rank": 2,
      "owner": "apache",
      "name": "ossie",
      "url": "https://github.com/apache/ossie",
      "description": "Apache Ossie, industry wide specification effort to standardize how we exchange semantic metadata across analytics, AI and BI platforms, providing a vendor neutral, single source of truth for semantic data",
      "language": "Python",
      "stars": "1,238",
      "forks": "151",
      "stars_today": "48 stars today"
    },
    {
      "rank": 3,
      "owner": "PostHog",
      "name": "posthog",
      "url": "https://github.com/PostHog/posthog",
      "description": "🦔 PostHog is the leading platform for building self-driving products. Our developer tools – AI observability, analytics, session replay, flags, experiments, error tracking, logs, and more – capture all the context agents need to diagnose problems, uncover opportunities, and ship fixes. Steer it all from Slack, web, desktop, or the MCP.",
      "language": "Python",
      "stars": "36,509",
      "forks": "3,023",
      "stars_today": "337 stars today"
    },
    {
      "rank": 4,
      "owner": "elder-plinius",
      "name": "G0DM0D3",
      "url": "https://github.com/elder-plinius/G0DM0D3",
      "description": "LIBERATED AI CHAT",
      "language": "TypeScript",
      "stars": "9,457",
      "forks": "2,252",
      "stars_today": "63 stars today"
    },
    {
      "rank": 5,
      "owner": "KnockOutEZ",
      "name": "wigolo",
      "url": "https://github.com/KnockOutEZ/wigolo",
      "description": "The go-to web for your AI coding agent — local-first search, fetch, crawl & research over MCP. No API keys, no cloud, $0/query. Public beta.",
      "language": "TypeScript",
      "stars": "1,131",
      "forks": "80",
      "stars_today": "192 stars today"
    },
    {
      "rank": 6,
      "owner": "codecrafters-io",
      "name": "build-your-own-x",
      "url": "https://github.com/codecrafters-io/build-your-own-x",
      "description": "Master programming by recreating your favorite technologies from scratch.",
      "language": "Markdown",
      "stars": "528,120",
      "forks": "49,976",
      "stars_today": "1,131 stars today"
    },
    {
      "rank": 7,
      "owner": "MoonshotAI",
      "name": "kimi-cli",
      "url": "https://github.com/MoonshotAI/kimi-cli",
      "description": "Kimi Code CLI is your next CLI agent.",
      "language": "Python",
      "stars": "9,401",
      "forks": "1,160",
      "stars_today": "48 stars today"
    }
  ]
}
